selenium_userway_web_accessibility/__init__.py
selenium_userway_web_accessibility/analysis.py
selenium_userway_web_accessibility/background_mode.py
selenium_userway_web_accessibility/get_violations.py
selenium_userway_web_accessibility/manual_mode.py
selenium_userway_web_accessibility/static_analysis.py
selenium_userway_web_accessibility/types.py
selenium_userway_web_accessibility/assets/index.iife.js
selenium_userway_web_accessibility/report/__init__.py
selenium_userway_web_accessibility/report/exception_reporter.py
selenium_userway_web_accessibility/report/json_reporter.py
selenium_userway_web_accessibility/report/origin_page_reporter.py
selenium_userway_web_accessibility/report/reporter.py
selenium_userway_web_accessibility/report/screenshot_reporter.py
selenium_userway_web_accessibility/utils/__init__.py
selenium_userway_web_accessibility/utils/base36_encode.py
selenium_userway_web_accessibility/utils/get_formatted_date.py
selenium_userway_web_accessibility/utils/is_ignore_url.py
selenium_userway_web_accessibility/utils/snake_to_camel_dict.py
selenium_userway_web_accessibility-0.0.5.dist-info/LICENSE.txt
selenium_userway_web_accessibility-0.0.5.dist-info/METADATA
selenium_userway_web_accessibility-0.0.5.dist-info/WHEEL
selenium_userway_web_accessibility-0.0.5.dist-info/top_level.txt
selenium_userway_web_accessibility-0.0.5.dist-info/RECORD
