Metadata-Version: 2.1
Name: selenium_userway_web_accessibility
Version: 0.0.5
Summary: UserWay Web Accessibility Plugin for Selenium
Author-email: UserWay <desk@support.userway.org>
License: UserWay Software License Agreement
Keywords: userway,accessibility,selenium
Classifier: Programming Language :: Python
Requires-Python: >=3.8
License-File: LICENSE.txt
Requires-Dist: selenium
Requires-Dist: humps
Requires-Dist: typing-extensions
